zepben/auth/__init__.py
zepben/auth/client/__init__.py
zepben/auth/client/zepben_token_fetcher.py
zepben/auth/common/__init__.py
zepben/auth/common/auth_exception.py
zepben/auth/common/auth_method.py
zepben/auth/common/auth_provider_config.py
zepben.auth-0.12.1.dist-info/LICENSE
zepben.auth-0.12.1.dist-info/METADATA
zepben.auth-0.12.1.dist-info/WHEEL
zepben.auth-0.12.1.dist-info/top_level.txt
zepben.auth-0.12.1.dist-info/RECORD
