Metadata-Version: 2.1
Name: zepben.auth
Version: 0.12.1
Summary: Utilities for authenticating to the Evolve App Server and Energy Workbench Server
Home-page: https://github.com/zepben/zepben-auth-python
Author: Ramon Bouckaert
Author-email: ramon.bouckaert@zepben.com
Requires-Python: >=3.9
License-File: LICENSE
Requires-Dist: requests<3.0.0,>=2.26.0
Requires-Dist: urllib3<1.27.0,>=1.26.6
Requires-Dist: PyJWT<2.2.0,>=2.1.0
Requires-Dist: dataclassy==0.6.2
Provides-Extra: test
Requires-Dist: pytest; extra == "test"
Requires-Dist: pytest-cov; extra == "test"
